microcsound/__init__.py
microcsound/config.py
microcsound/handlers.py
microcsound/helpers.py
microcsound/main.py
microcsound/parser.py
microcsound/state.py
microcsound/tests.py
microcsound/share/data/JI_robot_fingers.mc
microcsound/share/data/ciconia.mc
microcsound/share/data/gabrieli_canzon_1_saw.mc
microcsound/share/data/microcsound.orc
microcsound/share/data/scale.mc
microcsound/share/doc/CHANGES
microcsound/share/doc/microcsound_tutorial.txt
microcsound-2.0.4.dist-info/METADATA
microcsound-2.0.4.dist-info/WHEEL
microcsound-2.0.4.dist-info/entry_points.txt
microcsound-2.0.4.dist-info/licenses/LICENSE.txt
microcsound-2.0.4.dist-info/RECORD
