Metadata-Version: 2.3
Name: microcsound
Version: 2.0.4
Summary: A tool for writing csound scores that can make handling microtones MUCH easier.
Project-URL: Homepage, https://untwelve.org/microcsound
Project-URL: Repository, https://github.com/akjmicro/microcsound
Author-email: Aaron Krister Johnson <akjmicro@gmail.com>
Maintainer-email: Aaron Krister Johnson <akjmicro@gmail.com>
License: Copyright 2017-2022 Aaron Krister Johnson <akjmicro@gmail.com>
License-File: LICENSE.txt
Keywords: csound,microtonal,microtonality
Requires-Python: >=3.8
Requires-Dist: pytest
